{
  "handle": "p142807",
  "title": "P142807",
  "collection": "Donaldson",
  "collectionHandle": "donaldson",
  "category": "Donaldson",
  "tags": [
    "Donaldson",
    "ff1225"
  ],
  "images": [
    "https://pub-f66ad83430274d9284d9172bc855e8cd.r2.dev/donaldson/000129_a80f625c4259.jpg",
    "https://pub-f66ad83430274d9284d9172bc855e8cd.r2.dev/donaldson/000130_db24b6919049.jpg"
  ],
  "variants": [
    {
      "title": "Fleetguard AF460 Air Filter Filter - Panel | Replaces the Donaldson P142807",
      "sku": "p142807-1",
      "image": "https://pub-f66ad83430274d9284d9172bc855e8cd.r2.dev/donaldson/000129_a80f625c4259.jpg",
      "vendor": "",
      "price": 23100,
      "partNumber": "AF460",
      "hsCode": "8421.31.00",
      "countryOfOrigin": "United States",
      "description": "​Fleetguard® AF460 panel air filter provides optimized airflow designed with OEM requirements. Protect your investment and extend the life of your equipment with a filter that delivers superior protection.",
      "specifications": [
        "Style: Air Panel",
        "Engine",
        "Media: Cellulose",
        "Efficiency 1: ISO 5011",
        "Length: 501.4 mm",
        "Efficiency 1 The efficiency of the element is shown using the Micron (µ) and Beta (β) ratings. The micron rating indicates the size of the particle being filtered and the beta rating the efficiency",
        "calculated as 1/β. E.g. a rating of β200 will be 99.5% efficient whereas β1000 would be 99.9%.: ISO 5011",
        "Media Type: Cellulose"
      ],
      "unitWeight": "7.45 kg",
      "shippingVolume": "0.0597 m³"
    },
    {
      "title": "Donaldson P142807 Air Panel, Engine",
      "sku": "p142807-2",
      "image": "https://pub-f66ad83430274d9284d9172bc855e8cd.r2.dev/donaldson/000130_db24b6919049.jpg",
      "vendor": "",
      "price": 0,
      "partNumber": "P142807",
      "hsCode": "8421.31.00",
      "countryOfOrigin": "United States",
      "description": "Genuine Donaldson P142807 Air Panel, Engine is designed to provide reliable performance in air panel, engine applications. Built with high-quality materials, it ensures consistent functionality and durability. Ideal for industrial, automotive, or heavy-duty environments, this component enhances system performance and longevity.",
      "specifications": [
        "Style: Air Panel",
        "Engine",
        "Media: Cellulose",
        "Efficiency 1: ISO 5011",
        "Length: 501.4 mm",
        "Efficiency 1 The efficiency of the element is shown using the Micron (µ) and Beta (β) ratings. The micron rating indicates the size of the particle being filtered and the beta rating the efficiency",
        "calculated as 1/β. E.g. a rating of β200 will be 99.5% efficient whereas β1000 would be 99.9%.: ISO 5011",
        "Media Type: Cellulose"
      ],
      "unitWeight": "",
      "shippingVolume": ""
    }
  ]
}