{
  "handle": "p177345",
  "title": "P177345",
  "collection": "Donaldson",
  "collectionHandle": "donaldson",
  "category": "Donaldson",
  "tags": [
    "Donaldson",
    "ff1225"
  ],
  "images": [
    "https://cdn.shopify.com/s/files/1/0592/2648/8986/files/Donaldson_Placeholder_f684465a-8391-4818-9863-f4b515a7da47.jpg?v=1714719760"
  ],
  "variants": [
    {
      "title": "Donaldson P177345 Lube Spin-On Full Flow",
      "sku": "p177345-1",
      "image": "https://cdn.shopify.com/s/files/1/0592/2648/8986/files/Donaldson_Placeholder_f684465a-8391-4818-9863-f4b515a7da47.jpg?v=1714719760",
      "vendor": "",
      "price": 0,
      "partNumber": "P177345",
      "hsCode": "8421.23.00",
      "countryOfOrigin": "Mexico",
      "description": "Genuine Donaldson P177345 Lube Spin-On Full Flow is engineered to deliver reliable performance and durability across a wide range of applications. Designed with high-quality materials, it ensures consistent functionality while meeting demanding operational requirements. Whether used in industrial, automotive, or heavy-duty settings, this component offers dependable operation and longevity. Its versatile design makes it suitable for various uses, supporting system efficiency and overall performance.",
      "specifications": [
        "Style: Lube Spin-On Full Flow",
        "Outer Diameter: 93.0 mm",
        "Length: 135.9 mm"
      ],
      "unitWeight": "0.57 kg",
      "shippingVolume": ""
    }
  ]
}