{
  "handle": "p2126041",
  "title": "P2126041",
  "collection": "Argo Hytos",
  "collectionHandle": "argo-hytos",
  "category": "Argo Hytos",
  "tags": [
    "Argo Hytos",
    "ff1225"
  ],
  "images": [
    "https://cdn.shopify.com/s/files/1/0592/2648/8986/files/FF212672B_665d4fda-70b8-474d-943a-c9df34684a52.jpg?v=1709692148"
  ],
  "variants": [
    {
      "title": "Filtrec R663C25B0 Return Filter | Replaces the Argo-Hytos P2126041",
      "sku": "p2126041-1",
      "image": "https://cdn.shopify.com/s/files/1/0592/2648/8986/files/FF212672B_665d4fda-70b8-474d-943a-c9df34684a52.jpg?v=1709692148",
      "vendor": "",
      "price": 14100,
      "partNumber": "R663C25B0",
      "hsCode": "8421.99.90",
      "countryOfOrigin": "Italy",
      "description": "Genuine Filtrec R663C25B0. This Filtrec element is designed to meet or exceed the quality and performance of brand OEM’s ensuring superior filtration performance and long-lasting durability. Engineered with their high performance media and a durable design, the R663C25B0 provides reliable and consistent performance over its lifespan, even in harsh operating environments. When you order from FilterFinder, you can trust that you are getting a reliable and high-quality replacement filter that will keep your system running smoothly.",
      "specifications": [
        "Style: Return Filter",
        "Outer Diameter: 118.0 mm",
        "Inner Diameter: 57.3 mm",
        "Length: 600.0 mm"
      ],
      "unitWeight": "",
      "shippingVolume": ""
    }
  ]
}