{
  "handle": "sa-19586",
  "title": "SA 19586",
  "collection": "Air Filters",
  "collectionHandle": "air-filters",
  "category": "Air Filters",
  "tags": [
    "Filter",
    "ff1225"
  ],
  "images": [
    "https://cdn.shopify.com/s/files/1/0592/2648/8986/files/md-7a793434-47e8-460a-97bc-a541754f723f.jpg?v=1723234984"
  ],
  "variants": [
    {
      "title": "HiFi Filter SA 19586 Air Filter",
      "sku": "sa-19586-1",
      "image": "https://cdn.shopify.com/s/files/1/0592/2648/8986/files/md-7a793434-47e8-460a-97bc-a541754f723f.jpg?v=1723234984",
      "vendor": "",
      "price": 2600,
      "partNumber": "SA 19586",
      "hsCode": "8421.99.90",
      "countryOfOrigin": "France",
      "description": "Genuine HiFi Filter SA 19586 Air Filter. Easy to install and replace, the SA 19586 is built to withstand demanding environments, offering long-lasting protection and reliability. Whether used in automotive, agricultural, construction, or industrial applications, this filter is an essential component for maintaining system health and performance.",
      "specifications": [
        "Style: AIR FILTER",
        "Dimension 1 (D1): 110.0 mm",
        "Dimension 2 (D2): 64.0 mm",
        "Dimension 3 (D3): 64.0 mm",
        "Height 1 (H1): 212.5 mm",
        "Height 2 (H2): 211.0 mm"
      ],
      "unitWeight": "0.36 kg",
      "shippingVolume": "0.0041 m³"
    }
  ]
}