{
  "handle": "saad-09003",
  "title": "SAAD 09003",
  "collection": "Air Filters",
  "collectionHandle": "air-filters",
  "category": "Air Filters",
  "tags": [
    "Filter",
    "ff1225"
  ],
  "images": [
    "https://pub-f66ad83430274d9284d9172bc855e8cd.r2.dev/air-filters/saad-09003-saad-09003-b09f31e3fd76.jpg"
  ],
  "variants": [
    {
      "title": "HiFi Filter SAAD 09003 Adapter",
      "sku": "saad-09003-1",
      "option1Value": "HiFi Filter SAAD 09003 Adapter",
      "image": "https://pub-f66ad83430274d9284d9172bc855e8cd.r2.dev/air-filters/saad-09003-saad-09003-b09f31e3fd76.jpg",
      "vendor": "",
      "price": 4000,
      "partNumber": "SAAD 09003",
      "hsCode": "8421.99.90",
      "countryOfOrigin": "France",
      "description": "Genuine HiFi Filter SAAD 09003 Adapter. Easy to install and replace, the SAAD 09003 is built to withstand demanding environments, offering long-lasting protection and reliability. Whether used in automotive, agricultural, construction, or industrial applications, this filter is an essential component for maintaining system health and performance.",
      "specifications": [
        "Style: ADAPTER"
      ],
      "unitWeight": "0.1 kg",
      "shippingVolume": "0.0005 m³"
    }
  ]
}