{
  "handle": "sab-544-set",
  "title": "SAB 544 SET",
  "collection": "Air Filters",
  "collectionHandle": "air-filters",
  "category": "Air Filters",
  "tags": [
    "Filter",
    "ff1225"
  ],
  "images": [
    "https://pub-f66ad83430274d9284d9172bc855e8cd.r2.dev/air-filters/sab-544-set-u-620-4-y-kit-a490cfc91fc4.jpg",
    "https://pub-f66ad83430274d9284d9172bc855e8cd.r2.dev/air-filters/sab-544-set-sd-70313-90f816580b8a.jpg"
  ],
  "variants": [
    {
      "title": "Mann Filter U 620/4 y KIT Urea Filter | Replaces the SF Filter SAB 544-SET",
      "sku": "sab-544-set-1",
      "option1Value": "Mann Filter U 620/4 y KIT Urea Filter | Replaces the SF Filter SAB 544-SET",
      "image": "https://pub-f66ad83430274d9284d9172bc855e8cd.r2.dev/air-filters/sab-544-set-u-620-4-y-kit-a490cfc91fc4.jpg",
      "vendor": "",
      "price": 5000,
      "partNumber": "U 620/4 y KIT",
      "hsCode": "8421.29.80",
      "countryOfOrigin": "Germany",
      "description": "The compact MANN-FILTER urea filters are characterized by high filter fineness, proven suitability for everyday use and a long service life. They protect system components against wear and failure and are resistant to frost and ammonia. MANN-FILTER urea filters are available for leading SCR systems in trucks and buses.",
      "specifications": [
        "Style: Urea Filter, Dimension A: 67.0 mm, Dimension C: 33.0 mm, Dimension D: 70.0 mm, Dimension H: 76.0 mm"
      ],
      "unitWeight": "",
      "shippingVolume": ""
    },
    {
      "title": "HiFi Filter SD 70313 Urea Filter | Replaces the SF Filter SAB 544-SET",
      "sku": "sab-544-set-2",
      "option1Value": "HiFi Filter SD 70313 Urea Filter | Replaces the SF Filter SAB 544-SET",
      "image": "https://pub-f66ad83430274d9284d9172bc855e8cd.r2.dev/air-filters/sab-544-set-sd-70313-90f816580b8a.jpg",
      "vendor": "",
      "price": 3900,
      "partNumber": "SD 70313",
      "hsCode": "8421.99.90",
      "countryOfOrigin": "France",
      "description": "The genuine HiFi Filter SD 70313 Urea Filter is HiFi's replacement to the SF Filter SAB 544-SET. Easy to install and replace, the SD 70313 is built to withstand demanding environments, offering long-lasting protection and reliability. Whether used in automotive, agricultural, construction, or industrial applications, this filter is an essential component for maintaining system health and performance.",
      "specifications": [
        "Style: UREA FILTER, Dimension 1 (D1): 69.0 mm, Dimension 2 (D2): 67.0 mm, Dimension 3 (D3): 33.0 mm, Height 1 (H1): 76.0 mm, Height 2 (H2): 67.0 mm"
      ],
      "unitWeight": "0.18 kg",
      "shippingVolume": "0.0007 m³"
    }
  ]
}