{
  "handle": "sao58480",
  "title": "SAO58480",
  "collection": "Air Filters",
  "collectionHandle": "air-filters",
  "category": "Air Filters",
  "tags": [
    "Filter",
    "ff1225"
  ],
  "images": [
    "https://cdn.shopify.com/s/files/1/0592/2648/8986/files/OS_25205078_afc508fa-3701-4e92-b431-00ee84520d5f.jpg?v=1742496240"
  ],
  "variants": [
    {
      "title": "HiFi Filter OS 5078 Air/Oil Separator | Replaces the SF Filter SAO58480",
      "sku": "sao58480-1",
      "image": "https://cdn.shopify.com/s/files/1/0592/2648/8986/files/OS_25205078_afc508fa-3701-4e92-b431-00ee84520d5f.jpg?v=1742496240",
      "vendor": "",
      "price": 127600,
      "partNumber": "OS 5078",
      "hsCode": "8421.99.90",
      "countryOfOrigin": "France",
      "description": "The genuine HiFi Filter OS 5078 Air/Oil Separator is HiFi's replacement to the SF Filter SAO58480. Easy to install and replace, the OS 5078 is built to withstand demanding environments, offering long-lasting protection and reliability. Whether used in automotive, agricultural, construction, or industrial applications, this filter is an essential component for maintaining system health and performance.",
      "specifications": [
        "Style: Air/Oil Separator"
      ],
      "unitWeight": "28.0 kg",
      "shippingVolume": "0.1984 m³"
    }
  ]
}