{
  "handle": "169601sh3xlf000v",
  "title": "169601SH3XLF000V",
  "collection": "Eppensteiner",
  "collectionHandle": "eppensteiner",
  "category": "Eppensteiner",
  "tags": [
    "Eppensteiner",
    "ff1225"
  ],
  "images": [
    "https://cdn.shopify.com/s/files/1/0592/2648/8986/files/FF200424B-NB_cab395ac-27e5-45f5-b80f-0938630f6726.jpg?v=1741943779",
    "https://cdn.shopify.com/s/files/1/0592/2648/8986/files/p167185.700.700_ce63e664-15b9-4403-a784-6e390f77d638.jpg?v=1741943779",
    "https://cdn.shopify.com/s/files/1/0592/2648/8986/files/D150B_f0739c46-9b6f-4ab2-aec8-159de43737d3.jpg?v=1741943779",
    "https://cdn.shopify.com/s/files/1/0592/2648/8986/files/md-9d8595a7-e9c1-4c71-9761-5902cf517e3c_a1ab2f8c-71d7-4f90-b69b-e78d89d2a8cd.jpg?v=1741943779",
    "https://cdn.shopify.com/s/files/1/0592/2648/8986/files/HF30002_0d19392d-5986-4d65-b216-878161c26651.jpg?v=1755779083",
    "https://cdn.shopify.com/s/files/1/0592/2648/8986/files/FF200424B-NB_6ee16a86-c0dc-44e9-a826-8f9be17b1c10.jpg?v=1748450497",
    "https://cdn.shopify.com/s/files/1/0592/2648/8986/files/p167185.700.700_2f50624b-9cae-4a0f-ba88-ebc31b0ed07d.jpg?v=1748450497",
    "https://cdn.shopify.com/s/files/1/0592/2648/8986/files/D150B_8820c5de-ade6-43c5-8cf7-677439ffa6b5.jpg?v=1748450497",
    "https://cdn.shopify.com/s/files/1/0592/2648/8986/files/md-9d8595a7-e9c1-4c71-9761-5902cf517e3c_dd98cb02-3228-432e-bb7d-407c63a38251.jpg?v=1748450497",
    "https://cdn.shopify.com/s/files/1/0592/2648/8986/files/HF30002_b2de3470-48ff-4508-9434-2a8da11db259.jpg?v=1755779084"
  ],
  "variants": [
    {
      "title": "MicroFit® UltraGen III MFHHP40088 Pressure Filter | Replaces the Eppensteiner 16.9601SH3XLF000V",
      "sku": "16-9601sh3xlf000v-1",
      "image": "https://cdn.shopify.com/s/files/1/0592/2648/8986/files/FF200424B-NB_6ee16a86-c0dc-44e9-a826-8f9be17b1c10.jpg?v=1748450497",
      "vendor": "MicroFit",
      "price": 19900,
      "partNumber": "MFHHP40088",
      "hsCode": "8421.99.90",
      "countryOfOrigin": "United Kingdom",
      "description": "The MICROFIT® UltraGen III MFHHP40088 is the MICROFIT® approved replacement to the Eppensteiner 16.9601SH3XLF000V. Engineered and manufactured in Great Britain the MFHHP40088 is designed to meet or exceed the quality and performance of OEM quality standards, ensuring superior filtration performance and the longest possible filter life. Building on over 50 years of filtration expertise, the UltraGen III series is the third generation of MICROFIT® filter media, delivering exceptional efficiency and reliability. FilterFinder is an approved distributor of MICROFIT® filters. With expert product knowledge, dedicated support, and a large stock availability, FilterFinder ensures you receive the parts you need when you need them, every time.",
      "specifications": [
        "Style: Pressure Filter",
        "Media: Glass Fiber",
        "Efficiency 1: 3µ @ β200",
        "Efficiency 2: 5µ @ β1000",
        "Outer Diameter: 78.0 mm",
        "Inner Diameter: 43.0 mm",
        "Length: 210.0 mm",
        "Δ Collapse Pressure: 210 bar",
        "Seal Material: Viton",
        "Temperature Range: -25 - +120°C",
        "Efficiency 1 The efficiency of the element is shown using the Micron (µ) and Beta (β) ratings. The micron rating indicates the size of the particle being filtered and the beta rating the efficiency",
        "calculated as 1/β. E.g. a rating of β200 will be 99.5% efficient whereas β1000 would be 99.9%.: 3µ @ β200",
        "Media Type: Glass Fiber",
        "Flow Direction: OUT-IN",
        "Collapse Pressure: 210 BAR",
        "Seal: Viton"
      ],
      "unitWeight": "2.65 kg",
      "shippingVolume": "0.0013 m³"
    },
    {
      "title": "Donaldson P167185 Hydraulic Filter, Cartridge | Replaces the Eppensteiner 169601SH3XLF000V",
      "sku": "169601sh3xlf000v-2",
      "image": "https://cdn.shopify.com/s/files/1/0592/2648/8986/files/p167185.700.700_ce63e664-15b9-4403-a784-6e390f77d638.jpg?v=1741943779",
      "vendor": "Donaldson",
      "price": 29200,
      "partNumber": "P167185",
      "hsCode": "8421.29.80.90",
      "countryOfOrigin": "United States",
      "description": "Genuine Donaldson P167185 Hydraulic Filter, Cartridge is designed to provide superior protection for your hydraulic system, effectively capturing contaminants to ensure clean fluid circulation. With high-quality filtration media, it extends equipment life, improves operational efficiency, and maintains fluid cleanliness even in the most demanding environments. Built for industrial, agricultural, and heavy-duty applications, this filter offers excellent dirt-holding capacity and flow efficiency. Its easy installation and maintenance help reduce downtime, making it a reliable choice for keeping hydraulic systems running smoothly.",
      "specifications": [
        "Style: Pressure Filter",
        "Media: Glass Fiber",
        "Efficiency 1: 3µ @ β200",
        "Efficiency 2: 5µ @ β1000",
        "Outer Diameter: 78.0 mm",
        "Inner Diameter: 43.0 mm",
        "Length: 210.0 mm",
        "Δ Collapse Pressure: 210 bar",
        "Seal Material: Viton",
        "Temperature Range: -25 - +120°C",
        "Efficiency 1 The efficiency of the element is shown using the Micron (µ) and Beta (β) ratings. The micron rating indicates the size of the particle being filtered and the beta rating the efficiency",
        "calculated as 1/β. E.g. a rating of β200 will be 99.5% efficient whereas β1000 would be 99.9%.: 3µ @ β200",
        "Media Type: Glass Fiber",
        "Flow Direction: OUT-IN",
        "Collapse Pressure: 210 BAR",
        "Seal: Viton"
      ],
      "unitWeight": "1.3 kg",
      "shippingVolume": "0.0021 m³"
    },
    {
      "title": "Filtrec D141G03BV Pressure Filter | Replaces the Eppensteiner 169601SH3XLF000V",
      "sku": "169601sh3xlf000v-3",
      "image": "https://cdn.shopify.com/s/files/1/0592/2648/8986/files/D150B_f0739c46-9b6f-4ab2-aec8-159de43737d3.jpg?v=1741943779",
      "vendor": "Filtrec",
      "price": 30100,
      "partNumber": "D141G03BV",
      "hsCode": "8421.99.90",
      "countryOfOrigin": "Italy",
      "description": "Genuine Filtrec D141G03BV. This Filtrec element is designed to meet or exceed the quality and performance of brand OEM’s ensuring superior filtration performance and long-lasting durability. Engineered with their high performance media and a durable design, the D141G03BV provides reliable and consistent performance over its lifespan, even in harsh operating environments. When you order from FilterFinder, you can trust that you are getting a reliable and high-quality replacement filter that will keep your system running smoothly.",
      "specifications": [
        "Style: Pressure Filter",
        "Media: Glass Fiber",
        "Efficiency 1: 3µ @ β200",
        "Efficiency 2: 5µ @ β1000",
        "Outer Diameter: 78.0 mm",
        "Inner Diameter: 43.0 mm",
        "Length: 210.0 mm",
        "Δ Collapse Pressure: 210 bar",
        "Seal Material: Viton",
        "Temperature Range: -25 - +120°C",
        "Efficiency 1 The efficiency of the element is shown using the Micron (µ) and Beta (β) ratings. The micron rating indicates the size of the particle being filtered and the beta rating the efficiency",
        "calculated as 1/β. E.g. a rating of β200 will be 99.5% efficient whereas β1000 would be 99.9%.: 3µ @ β200",
        "Media Type: Glass Fiber",
        "Flow Direction: OUT-IN",
        "Collapse Pressure: 210 BAR",
        "Seal: Viton"
      ],
      "unitWeight": "1.2 kg",
      "shippingVolume": "0.0013 m³"
    },
    {
      "title": "HiFi Filter SH 57132 V Pressure Filter | Replaces the Eppensteiner 169601SH3XLF000V",
      "sku": "169601sh3xlf000v-4",
      "image": "https://cdn.shopify.com/s/files/1/0592/2648/8986/files/md-9d8595a7-e9c1-4c71-9761-5902cf517e3c_a1ab2f8c-71d7-4f90-b69b-e78d89d2a8cd.jpg?v=1741943779",
      "vendor": "HiFi Filter",
      "price": 34500,
      "partNumber": "SH 57132 V",
      "hsCode": "8421.99.90",
      "countryOfOrigin": "France",
      "description": "Genuine HiFi Filter SH 57132 V Hydraulic Filter. Engineered to protect and optimize the performance of hydraulic systems, this filter delivers exceptional contamination control. Premium filter media captures fine particles and debris that could compromise system integrity, helping to extend the lifespan of critical hydraulic components. By maintaining fluid cleanliness, it reduces wear and tear while supporting consistent pressure levels throughout the system. Perfect for a wide range of hydraulic applications—from industrial machinery to heavy-duty equipment—this filter provides reliable performance even under high-pressure conditions. Its robust construction ensures long-lasting durability, helping to minimize downtime and maintenance costs while maximizing operational efficiency.",
      "specifications": [
        "Style: Pressure Filter",
        "Media: Glass Fiber",
        "Efficiency 1: 3µ @ β200",
        "Efficiency 2: 5µ @ β1000",
        "Outer Diameter: 78.0 mm",
        "Inner Diameter: 43.0 mm",
        "Length: 210.0 mm",
        "Δ Collapse Pressure: 210 bar",
        "Seal Material: Viton",
        "Temperature Range: -25 - +120°C",
        "Efficiency 1 The efficiency of the element is shown using the Micron (µ) and Beta (β) ratings. The micron rating indicates the size of the particle being filtered and the beta rating the efficiency",
        "calculated as 1/β. E.g. a rating of β200 will be 99.5% efficient whereas β1000 would be 99.9%.: 3µ @ β200",
        "Media Type: Glass Fiber",
        "Flow Direction: OUT-IN",
        "Collapse Pressure: 210 BAR",
        "Seal: Viton"
      ],
      "unitWeight": "1.28 kg",
      "shippingVolume": "0.0017 m³"
    },
    {
      "title": "Fleetguard HF30002 Hydraulic Filters | Replaces the Eppensteiner 169601SH3XLF000V",
      "sku": "169601sh3xlf000v-5",
      "image": "https://cdn.shopify.com/s/files/1/0592/2648/8986/files/HF30002_0d19392d-5986-4d65-b216-878161c26651.jpg?v=1755779083",
      "vendor": "Fleetguard",
      "price": 38000,
      "partNumber": "HF30002",
      "hsCode": "8421.23.00",
      "countryOfOrigin": "United States",
      "description": "Fleetguard® HF30002 premium hydraulic spin-on filter with cellulose media is designed to help keep your precision hydraulic systems running as intended, providing a solution for various applications.  This filter meets or exceeds the equipment OEM quality and performance and is the first aftermarket replacement available on the market today, bringing your operation top-quality performance and an overall unbeatable total cost of ownership.",
      "specifications": [
        "Style: Pressure Filter",
        "Media: Glass Fiber",
        "Efficiency 1: 3µ @ β200",
        "Efficiency 2: 5µ @ β1000",
        "Outer Diameter: 78.0 mm",
        "Inner Diameter: 43.0 mm",
        "Length: 210.0 mm",
        "Δ Collapse Pressure: 210 bar",
        "Seal Material: Viton",
        "Temperature Range: -25 - +120°C",
        "Efficiency 1 The efficiency of the element is shown using the Micron (µ) and Beta (β) ratings. The micron rating indicates the size of the particle being filtered and the beta rating the efficiency",
        "calculated as 1/β. E.g. a rating of β200 will be 99.5% efficient whereas β1000 would be 99.9%.: 3µ @ β200",
        "Media Type: Glass Fiber",
        "Flow Direction: OUT-IN",
        "Collapse Pressure: 210 BAR",
        "Seal: Viton"
      ],
      "unitWeight": "1.6 kg",
      "shippingVolume": "0.0033 m³"
    }
  ]
}