{
  "handle": "169800th3sle000p",
  "title": "169800TH3SLE000P",
  "collection": "Eppensteiner",
  "collectionHandle": "eppensteiner",
  "category": "Eppensteiner",
  "tags": [
    "Eppensteiner",
    "ff1225"
  ],
  "images": [
    "https://pub-b8cf8833c33242d391ce938e51d3c590.r2.dev/eppensteiner/017810_4705a5c1d330.jpg",
    "https://pub-b8cf8833c33242d391ce938e51d3c590.r2.dev/eppensteiner/017811_6a3d21906e4b.jpg",
    "https://pub-b8cf8833c33242d391ce938e51d3c590.r2.dev/eppensteiner/017812_8e7f28bcafce.jpg",
    "https://pub-b8cf8833c33242d391ce938e51d3c590.r2.dev/eppensteiner/017815_a09820f321a6.jpg",
    "https://pub-b8cf8833c33242d391ce938e51d3c590.r2.dev/eppensteiner/017816_a39e9be23686.jpg",
    "https://pub-b8cf8833c33242d391ce938e51d3c590.r2.dev/eppensteiner/017817_bcce6d0e8459.jpg"
  ],
  "variants": [
    {
      "title": "MicroFit® UltraGen III MFHLP30109 Pressure Filter | Replaces the Eppensteiner 16.9800TH3SLE000P",
      "sku": "16-9800th3sle000p-1",
      "image": "https://pub-b8cf8833c33242d391ce938e51d3c590.r2.dev/eppensteiner/017815_a09820f321a6.jpg",
      "vendor": "",
      "price": 7200,
      "partNumber": "MFHLP30109",
      "hsCode": "8421.99.90",
      "countryOfOrigin": "United Kingdom",
      "description": "The MICROFIT® UltraGen III MFHLP30109 is the MICROFIT® approved replacement to the Eppensteiner 16.9800TH3SLE000P. Engineered and manufactured in Great Britain the MFHLP30109 is designed to meet or exceed the quality and performance of OEM quality standards, ensuring superior filtration performance and the longest possible filter life. Building on over 50 years of filtration expertise, the UltraGen III series is the third generation of MICROFIT® filter media, delivering exceptional efficiency and reliability. FilterFinder is an approved distributor of MICROFIT® filters. With expert product knowledge, dedicated support, and a large stock availability, FilterFinder ensures you receive the parts you need when you need them, every time.",
      "specifications": [
        "Style: Pressure Filter",
        "Media: Glass Fiber",
        "Efficiency 1: 3µ @ β200",
        "Efficiency 2: 5µ @ β1000",
        "Outer Diameter: 50.0 mm",
        "Inner Diameter: 24.5 mm",
        "Length: 329.0 mm",
        "Δ Collapse Pressure: 21 bar",
        "Seal Material: Nitrile",
        "Temperature Range: -30 - +100°C",
        "Efficiency 1 The efficiency of the element is shown using the Micron (µ) and Beta (β) ratings. The micron rating indicates the size of the particle being filtered and the beta rating the efficiency",
        "calculated as 1/β. E.g. a rating of β200 will be 99.5% efficient whereas β1000 would be 99.9%.: 3µ @ β200",
        "Media Type: Glass Fiber",
        "Flow Direction: OUT-IN",
        "Collapse Pressure: 21 BAR",
        "Seal: Nitrile"
      ],
      "unitWeight": "1.15 kg",
      "shippingVolume": "0.0008 m³"
    },
    {
      "title": "Filtrec D122G03A Pressure Filter | Replaces the Eppensteiner 169800TH3SLE000P",
      "sku": "169800th3sle000p-2",
      "image": "https://pub-b8cf8833c33242d391ce938e51d3c590.r2.dev/eppensteiner/017811_6a3d21906e4b.jpg",
      "vendor": "",
      "price": 11600,
      "partNumber": "D122G03A",
      "hsCode": "8421.99.90",
      "countryOfOrigin": "Italy",
      "description": "Genuine Filtrec D122G03A. This Filtrec element is designed to meet or exceed the quality and performance of brand OEM’s ensuring superior filtration performance and long-lasting durability. Engineered with their high performance media and a durable design, the D122G03A provides reliable and consistent performance over its lifespan, even in harsh operating environments. When you order from FilterFinder, you can trust that you are getting a reliable and high-quality replacement filter that will keep your system running smoothly.",
      "specifications": [
        "Style: Pressure Filter",
        "Media: Glass Fiber",
        "Efficiency 1: 3µ @ β200",
        "Efficiency 2: 5µ @ β1000",
        "Outer Diameter: 50.0 mm",
        "Inner Diameter: 24.5 mm",
        "Length: 329.0 mm",
        "Δ Collapse Pressure: 21 bar",
        "Seal Material: Nitrile",
        "Temperature Range: -30 - +100°C",
        "Efficiency 1 The efficiency of the element is shown using the Micron (µ) and Beta (β) ratings. The micron rating indicates the size of the particle being filtered and the beta rating the efficiency",
        "calculated as 1/β. E.g. a rating of β200 will be 99.5% efficient whereas β1000 would be 99.9%.: 3µ @ β200",
        "Media Type: Glass Fiber",
        "Flow Direction: OUT-IN",
        "Collapse Pressure: 21 BAR",
        "Seal: Nitrile"
      ],
      "unitWeight": "0.52 kg",
      "shippingVolume": "0.0008 m³"
    },
    {
      "title": "Fleetguard HF30522 Hydraulic Filters | Replaces the Eppensteiner 169800TH3SLE000P",
      "sku": "169800th3sle000p-3",
      "image": "https://pub-b8cf8833c33242d391ce938e51d3c590.r2.dev/eppensteiner/017812_8e7f28bcafce.jpg",
      "vendor": "",
      "price": 26400,
      "partNumber": "HF30522",
      "hsCode": "8421.23.00",
      "countryOfOrigin": "United States",
      "description": "Fleetguard® HF30522 hydraulic cartridge filter with synthetic media is designed to help keep your precision hydraulic systems running as intended, providing a solution for various applications.  This filter meets or exceeds the equipment OEM quality and performance and is the first aftermarket replacement available on the market today, bringing your operation top-quality performance and an overall unbeatable total cost of ownership.",
      "specifications": [
        "Style: Pressure Filter",
        "Media: Glass Fiber",
        "Efficiency 1: 3µ @ β200",
        "Efficiency 2: 5µ @ β1000",
        "Outer Diameter: 50.0 mm",
        "Inner Diameter: 24.5 mm",
        "Length: 329.0 mm",
        "Δ Collapse Pressure: 21 bar",
        "Seal Material: Nitrile",
        "Temperature Range: -30 - +100°C",
        "Efficiency 1 The efficiency of the element is shown using the Micron (µ) and Beta (β) ratings. The micron rating indicates the size of the particle being filtered and the beta rating the efficiency",
        "calculated as 1/β. E.g. a rating of β200 will be 99.5% efficient whereas β1000 would be 99.9%.: 3µ @ β200",
        "Media Type: Glass Fiber",
        "Flow Direction: OUT-IN",
        "Collapse Pressure: 21 BAR",
        "Seal: Nitrile"
      ],
      "unitWeight": "0.91 kg",
      "shippingVolume": "0.005 m³"
    }
  ]
}