{
  "handle": "sa10751",
  "title": "SA 10751",
  "collection": "Air Filters",
  "collectionHandle": "air-filters",
  "category": "Air Filters",
  "tags": [
    "Filter",
    "ff1225"
  ],
  "images": [
    "https://cdn.shopify.com/s/files/1/0592/2648/8986/files/HiFi-No-Img-800x800_a8e63e44-de94-4db1-aa30-a9a9146d8af6.jpg?v=1766021156",
    "https://cdn.shopify.com/s/files/1/0592/2648/8986/files/p181114.700.700_e6a09453-cc60-4bda-a799-07513552a971.jpg?v=1766021156",
    "https://cdn.shopify.com/s/files/1/0592/2648/8986/files/AF801_a83ee159-85fb-4f94-a9f6-9b93b25dd594.jpg?v=1766021156"
  ],
  "variants": [
    {
      "title": "HiFi Filter SA 10751 Air Filter",
      "sku": "sa-10751-1",
      "image": "https://cdn.shopify.com/s/files/1/0592/2648/8986/files/HiFi-No-Img-800x800_a8e63e44-de94-4db1-aa30-a9a9146d8af6.jpg?v=1766021156",
      "vendor": "",
      "price": 18500,
      "partNumber": "SA 10751",
      "hsCode": "8421.99.90",
      "countryOfOrigin": "France",
      "description": "Genuine HiFi Filter SA 10751 Air Filter. Easy to install and replace, the SA 10751 is built to withstand demanding environments, offering long-lasting protection and reliability. Whether used in automotive, agricultural, construction, or industrial applications, this filter is an essential component for maintaining system health and performance.",
      "specifications": [
        "Style: Air Filter"
      ],
      "unitWeight": "4.66 kg",
      "shippingVolume": "0.0591 m³"
    },
    {
      "title": "Donaldson P181114 Air Filter, Primary Round | Replaces the HiFi Filter SA 10751",
      "sku": "sa-10751-2",
      "image": "https://cdn.shopify.com/s/files/1/0592/2648/8986/files/p181114.700.700_e6a09453-cc60-4bda-a799-07513552a971.jpg?v=1766021156",
      "vendor": "",
      "price": 13000,
      "partNumber": "P181114",
      "hsCode": "8421.31.00.90",
      "countryOfOrigin": "United States",
      "description": "Why Choose Donaldson Air Filters? Strong, pliable gasket is compressed against the air cleaner housing to create a tight seal. • High-efficiency cellulose media performs across a wide range of heavy-duty engine applications. • Corrosion resistant, coated steel liners support media during operation and help maximize airflow. • Pleatloc™ feature ensures uniform pleat spacing and prevents media from bunching to promote longer service life.",
      "specifications": [
        "Style: Air Filter"
      ],
      "unitWeight": "4.52 kg",
      "shippingVolume": "0.0595 m³"
    },
    {
      "title": "Fleetguard AF801 Air Filter, Primary | Replaces the HiFi Filter SA 10751",
      "sku": "sa-10751-3",
      "image": "https://cdn.shopify.com/s/files/1/0592/2648/8986/files/AF801_a83ee159-85fb-4f94-a9f6-9b93b25dd594.jpg?v=1766021156",
      "vendor": "",
      "price": 11100,
      "partNumber": "AF801",
      "hsCode": "8421.31.00",
      "countryOfOrigin": "United States",
      "description": "​Fleetguard® AF801 axial seal primary air filter ensures a proper seal and prevent leaks to prevent airborne contaminants from reaching the combustion chamber.",
      "specifications": [
        "Style: Air Filter"
      ],
      "unitWeight": "4.52 kg",
      "shippingVolume": ""
    }
  ]
}