{
  "handle": "sa11155",
  "title": "SA 11155",
  "collection": "Air Filters",
  "collectionHandle": "air-filters",
  "category": "Air Filters",
  "tags": [
    "Filter",
    "ff1225"
  ],
  "images": [
    "https://pub-b8cf8833c33242d391ce938e51d3c590.r2.dev/air-filters/008167_6c6b810e9a4b.jpg",
    "https://pub-b8cf8833c33242d391ce938e51d3c590.r2.dev/air-filters/008168_0bbdd2531233.jpg"
  ],
  "variants": [
    {
      "title": "HiFi Filter SA 11155 Air Filter",
      "sku": "sa-11155-1",
      "image": "https://pub-b8cf8833c33242d391ce938e51d3c590.r2.dev/air-filters/008167_6c6b810e9a4b.jpg",
      "vendor": "",
      "price": 2400,
      "partNumber": "SA 11155",
      "hsCode": "8421.99.90",
      "countryOfOrigin": "France",
      "description": "Genuine HiFi Filter SA 11155 Air Filter. Easy to install and replace, the SA 11155 is built to withstand demanding environments, offering long-lasting protection and reliability. Whether used in automotive, agricultural, construction, or industrial applications, this filter is an essential component for maintaining system health and performance.",
      "specifications": [
        "Style: AIR FILTER",
        "Dimension 1 (D1): 126.0 mm",
        "Dimension 2 (D2): 103.0 mm",
        "Dimension 3 (D3): 63.0 mm",
        "Height 1 (H1): 153.0 mm",
        "Height 2 (H2): 148.0 mm",
        "Height 3 (H3): 128.0 mm"
      ],
      "unitWeight": "0.42 kg",
      "shippingVolume": "0.0035 m³"
    },
    {
      "title": "Donaldson E500667 Air Filter, Primary Finned | Replaces the HiFi Filter SA 11155",
      "sku": "sa-11155-2",
      "image": "https://pub-b8cf8833c33242d391ce938e51d3c590.r2.dev/air-filters/008168_0bbdd2531233.jpg",
      "vendor": "",
      "price": 3000,
      "partNumber": "E500667",
      "hsCode": "8421.31.00.90",
      "countryOfOrigin": "Czechia",
      "description": "Genuine Donaldson E500667 Air Filter, Primary Finned features a finned design that maximizes surface area for enhanced dust-holding capacity and airflow. It effectively filters airborne contaminants, ensuring clean intake air and improving engine performance and longevity. Ideal for engines operating in dusty environments, this primary air filter offers durable construction and long service intervals. Its efficient filtration helps reduce engine wear and supports consistent power output.",
      "specifications": [
        "Style: Air Filter"
      ],
      "unitWeight": "0.44 kg",
      "shippingVolume": "0.0044 m³"
    }
  ]
}