{
  "handle": "sa18254",
  "title": "SA 18254",
  "collection": "Air Filters",
  "collectionHandle": "air-filters",
  "category": "Air Filters",
  "tags": [
    "Filter",
    "ff1225"
  ],
  "images": [
    "https://cdn.shopify.com/s/files/1/0592/2648/8986/files/md-6df25495-0888-48ed-ad22-ce923f872aef.jpg?v=1762811636"
  ],
  "variants": [
    {
      "title": "HiFi Filter SA 18254 Air Filter",
      "sku": "sa-18254-1",
      "image": "https://cdn.shopify.com/s/files/1/0592/2648/8986/files/md-6df25495-0888-48ed-ad22-ce923f872aef.jpg?v=1762811636",
      "vendor": "",
      "price": 3800,
      "partNumber": "SA 18254",
      "hsCode": "8421.99.90",
      "countryOfOrigin": "France",
      "description": "Genuine HiFi Filter SA 18254 Air Filter. Easy to install and replace, the SA 18254 is built to withstand demanding environments, offering long-lasting protection and reliability. Whether used in automotive, agricultural, construction, or industrial applications, this filter is an essential component for maintaining system health and performance.",
      "specifications": [
        "Style: AIR FILTER",
        "Dimension 1 (D1): 154.0 mm",
        "Dimension 2 (D2): 147.0 mm",
        "Dimension 3 (D3): 122.0 mm",
        "Height 1 (H1): 464.0 mm",
        "Height 2 (H2): 445.0 mm",
        "Height 3 (H3): 9.0 mm"
      ],
      "unitWeight": "1.14 kg",
      "shippingVolume": "0.0116 m³"
    }
  ]
}