{
  "handle": "sa8419",
  "title": "SA 8419",
  "collection": "Air Filters",
  "collectionHandle": "air-filters",
  "category": "Air Filters",
  "tags": [
    "Filter",
    "ff1225"
  ],
  "images": [
    "https://cdn.shopify.com/s/files/1/0592/2648/8986/files/md-5993a70a-4453-40ea-a643-cc3763478194.jpg?v=1723213219"
  ],
  "variants": [
    {
      "title": "HiFi Filter SA 8419 Air Filter",
      "sku": "sa-8419-1",
      "image": "https://cdn.shopify.com/s/files/1/0592/2648/8986/files/md-5993a70a-4453-40ea-a643-cc3763478194.jpg?v=1723213219",
      "vendor": "",
      "price": 1200,
      "partNumber": "SA 8419",
      "hsCode": "8421.99.90",
      "countryOfOrigin": "France",
      "description": "Genuine HiFi Filter SA 8419 Air Filter. Easy to install and replace, the SA 8419 is built to withstand demanding environments, offering long-lasting protection and reliability. Whether used in automotive, agricultural, construction, or industrial applications, this filter is an essential component for maintaining system health and performance.",
      "specifications": [
        "Style: AIR FILTER",
        "Dimension 1 (D1): 237.0 mm",
        "Dimension 2 (D2): 170.0 mm",
        "Dimension 3 (D3): 170.0 mm",
        "Height 1 (H1): 67.0 mm",
        "Height 2 (H2): 57.0 mm"
      ],
      "unitWeight": "0.44 kg",
      "shippingVolume": "0.004 m³"
    }
  ]
}