{
  "handle": "sacl01002",
  "title": "SACL 01002",
  "collection": "Air Filters",
  "collectionHandle": "air-filters",
  "category": "Air Filters",
  "tags": [
    "Filter",
    "ff1225"
  ],
  "images": [
    "https://cdn.shopify.com/s/files/1/0592/2648/8986/files/HiFi-No-Img-800x800_76191b93-d1b2-464a-b607-ec27384fa47e.jpg?v=1766022327"
  ],
  "variants": [
    {
      "title": "HiFi Filter SACL 01002 Clip Nut",
      "sku": "sacl-01002-1",
      "image": "https://cdn.shopify.com/s/files/1/0592/2648/8986/files/HiFi-No-Img-800x800_76191b93-d1b2-464a-b607-ec27384fa47e.jpg?v=1766022327",
      "vendor": "",
      "price": 1400,
      "partNumber": "SACL 01002",
      "hsCode": "8421.99.90",
      "countryOfOrigin": "France",
      "description": "Genuine HiFi Filter SACL 01002 Clip Nut. Easy to install and replace, the SACL 01002 is built to withstand demanding environments, offering long-lasting protection and reliability. Whether used in automotive, agricultural, construction, or industrial applications, this filter is an essential component for maintaining system health and performance.",
      "specifications": [
        "Style: CLIP NUT"
      ],
      "unitWeight": "",
      "shippingVolume": ""
    }
  ]
}