{
  "handle": "sacv02053",
  "title": "SACV 02053",
  "collection": "Air Filters",
  "collectionHandle": "air-filters",
  "category": "Air Filters",
  "tags": [
    "Filter",
    "ff1225"
  ],
  "images": [
    "https://pub-b8cf8833c33242d391ce938e51d3c590.r2.dev/air-filters/002621_2bd42ee8aefe.jpg"
  ],
  "variants": [
    {
      "title": "HiFi Filter SACV 02053 Cover",
      "sku": "sacv-02053-1",
      "image": "https://pub-b8cf8833c33242d391ce938e51d3c590.r2.dev/air-filters/002621_2bd42ee8aefe.jpg",
      "vendor": "",
      "price": 0,
      "partNumber": "SACV 02053",
      "hsCode": "8421.99.90",
      "countryOfOrigin": "France",
      "description": "Genuine HiFi Filter SACV 02053 Cover. Easy to install and replace, the SACV 02053 is built to withstand demanding environments, offering long-lasting protection and reliability. Whether used in automotive, agricultural, construction, or industrial applications, this filter is an essential component for maintaining system health and performance.",
      "specifications": [
        "Style: COVER"
      ],
      "unitWeight": "",
      "shippingVolume": ""
    }
  ]
}