{
  "handle": "sao57232",
  "title": "SAO57232",
  "collection": "Air Filters",
  "collectionHandle": "air-filters",
  "category": "Air Filters",
  "tags": [
    "Filter",
    "ff1225"
  ],
  "images": [
    "https://pub-b8cf8833c33242d391ce938e51d3c590.r2.dev/air-filters/000785_c67578404de9.jpg",
    "https://pub-b8cf8833c33242d391ce938e51d3c590.r2.dev/air-filters/001892_a4f47f5045fa.jpg"
  ],
  "variants": [
    {
      "title": "HiFi Filter OS 5235 Air/Oil Separator | Replaces the SF Filter SAO 57232",
      "sku": "sao-57232-1",
      "image": "https://pub-b8cf8833c33242d391ce938e51d3c590.r2.dev/air-filters/001892_a4f47f5045fa.jpg",
      "vendor": "",
      "price": 15600,
      "partNumber": "OS 5235",
      "hsCode": "8421.99.90",
      "countryOfOrigin": "France",
      "description": "The genuine HiFi Filter OS 5235 Air/Oil Separator is HiFi's replacement to the SF Filter SAO 57232. Easy to install and replace, the OS 5235 is built to withstand demanding environments, offering long-lasting protection and reliability. Whether used in automotive, agricultural, construction, or industrial applications, this filter is an essential component for maintaining system health and performance.",
      "specifications": [
        "Style: AIR/OIL SEPARATOR",
        "Dimension 1 (D1): 165.0 mm",
        "Dimension 2 (D2): 110.0 mm",
        "Dimension 3 (D3): 58.0 mm",
        "Height 1 (H1): 250.0 mm"
      ],
      "unitWeight": "1.78 kg",
      "shippingVolume": "0.0117 m³"
    }
  ]
}